marvin/__init__.py
marvin/database.py
marvin/defaults.py
marvin/instructions.md
marvin/instructions.py
marvin/prompts.py
marvin/py.typed
marvin/settings.py
marvin/thread.py
marvin/_internal/deprecation.py
marvin/_internal/integrations/README.md
marvin/_internal/integrations/fastmcp.py
marvin/_internal/integrations/mcp.py
marvin/agents/CLAUDE.md
marvin/agents/__init__.py
marvin/agents/actor.py
marvin/agents/agent.py
marvin/agents/names.py
marvin/agents/team.py
marvin/beta/__init__.py
marvin/cli/__init__.py
marvin/cli/config.py
marvin/cli/dev.py
marvin/cli/main.py
marvin/cli/migrations.py
marvin/engine/CLAUDE.md
marvin/engine/__init__.py
marvin/engine/end_turn.py
marvin/engine/events.py
marvin/engine/llm.py
marvin/engine/orchestrator.py
marvin/engine/streaming.py
marvin/fns/__init__.py
marvin/fns/cast.py
marvin/fns/classify.py
marvin/fns/extract.py
marvin/fns/fn.py
marvin/fns/generate.py
marvin/fns/plan.py
marvin/fns/run.py
marvin/fns/say.py
marvin/fns/summarize.py
marvin/handlers/__init__.py
marvin/handlers/handlers.py
marvin/handlers/print_handler.py
marvin/handlers/queue_handler.py
marvin/memory/__init__.py
marvin/memory/memory.py
marvin/memory/providers/__init__.py
marvin/memory/providers/chroma.py
marvin/memory/providers/lance.py
marvin/memory/providers/postgres.py
marvin/memory/providers/qdrant.py
marvin/tasks/CLAUDE.md
marvin/tasks/__init__.py
marvin/tasks/task.py
marvin/templates/agent.jinja
marvin/templates/memory.jinja
marvin/templates/system.jinja
marvin/templates/task.jinja
marvin/templates/team.jinja
marvin/tools/CLAUDE.md
marvin/tools/__init__.py
marvin/tools/thread.py
marvin/tools/interactive/cli.py
marvin/utilities/__init__.py
marvin/utilities/asyncio.py
marvin/utilities/jinja.py
marvin/utilities/jsonschema.py
marvin/utilities/logging.py
marvin/utilities/models.py
marvin/utilities/testing.py
marvin/utilities/tools.py
marvin/utilities/types.py
marvin-3.2.5.dist-info/METADATA
marvin-3.2.5.dist-info/WHEEL
marvin-3.2.5.dist-info/entry_points.txt
marvin-3.2.5.dist-info/licenses/LICENSE
marvin-3.2.5.dist-info/RECORD
