Metadata-Version: 2.4
Name: marvin
Version: 3.2.5
Summary: a simple and powerful tool to get things done with AI
License:                                  Apache License
License-File: LICENSE
Requires-Python: >=3.10
Requires-Dist: aiosqlite>=0.20.0
Requires-Dist: alembic>=1.12.0
Requires-Dist: jinja2>=3.1.4
Requires-Dist: partial-json-parser>=0.2.1.1.post5
Requires-Dist: pydantic-ai>=1.9.0
Requires-Dist: pydantic-settings>=2.6.1
Requires-Dist: pydantic[email]>=2.10.6
Requires-Dist: rich>=13.9.4
Requires-Dist: sqlalchemy[asyncio]>=2.0.36
Requires-Dist: typer>=0.15.1
Provides-Extra: audio
Requires-Dist: pyaudio>=0.2.14; extra == 'audio'
Provides-Extra: mcp
Requires-Dist: fastmcp; extra == 'mcp'
Provides-Extra: slackbot
Requires-Dist: slackbot; extra == 'slackbot'
